{"BGE_County": {"data": 200, "date": null, "metadata": null, "created": "2020-05-07 11:36", "data age (min)": 0.6}, "BGE_ZIP": {"data": 200, "date": null, "metadata": null, "created": "2020-05-07 11:36", "data age (min)": 0.6}, "CTK_County": {"data": 200, "date": null, "metadata": null, "created": "2020-05-07 11:30", "data age (min)": 6.6}, "CTK_ZIP": {"data": 200, "date": null, "metadata": null, "created": "2020-05-07 11:30", "data age (min)": 6.6}, "DEL_County": {"data": 200, "date": 200, "metadata": 200, "created": "2020-05-07 11:25", "data age (min)": 11.6}, "DEL_ZIP": {"data": 200, "date": 200, "metadata": 200, "created": "2020-05-07 11:25", "data age (min)": 11.6}, "EUC_County": {"data": 200, "date": null, "metadata": null, "created": "2020-05-07 11:36", "data age (min)": 0.6}, "EUC_ZIP": {"data": 200, "date": null, "metadata": null, "created": "2020-05-07 11:36", "data age (min)": 0.6}, "FES_County": {"data": 200, "date": null, "metadata": null, "created": "2020-05-07 11:35", "data age (min)": 1.6}, "FES_ZIP": {"data": 200, "date": null, "metadata": null, "created": "2020-05-07 11:35", "data age (min)": 1.6}, "PEP_County": {"data": 200, "date": 200, "metadata": 200, "created": "2020-05-07 11:30", "data age (min)": 6.6}, "PEP_ZIP": {"data": 200, "date": 200, "metadata": 200, "created": "2020-05-07 11:30", "data age (min)": 6.6}, "SME_County": {"data": 200, "date": 200, "metadata": 200, "created": "2020-05-07 11:26", "data age (min)": 10.6}, "SME_ZIP": {"data": 200, "date": 200, "metadata": 200, "created": "2020-05-07 11:26", "data age (min)": 10.6}}